[
    {
        "band": 28,
        "providers": [
            {
                "provider": {
                    "name": "3",
                    "longName": "Hi3G Denmark",
                    "homePage": "https://www.3.dk/",
                    "backgroundColor": "#f37423",
                    "textColor": "white" 
                },
                "frequency": {
                    "downLink": {
                        "start": 758,
                        "end": 768
                    },
                    "upLink": {
                        "start": 703,
                        "end": 713
                    }
                },
                "valid": {
                    "start": "2020-04-04",
                    "end": "2040-04-03"
                },
                "source": [
                    {
                        "name": "Danish Energy Agency",
                        "url": "https://ens.dk/sites/ens.dk/files/Tele/700-900_mhz-tilladelse_-_hi3g.pdf"
                    }
                ]
            },
            {
                "provider": {
                    "name": "TT",
                    "longName": "TT-Netværket",
                    "homePage": "https://www.tt-network.dk/",
                    "backgroundColor": "#663989",
                    "textColor": "white" 
                },
                "frequency": {
                    "downLink": {
                        "start": 768,
                        "end": 773
                    },
                    "upLink": {
                        "start": 713,
                        "end": 718
                    }
                },
                "valid": {
                    "start": "2020-04-04",
                    "end": "2040-04-03"
                },
                "source": [
                    {
                        "name": "Danish Energy Agency",
                        "url": "https://ens.dk/sites/ens.dk/files/Tele/700-900_mhz-tilladelse_-tt-netvaerket.pdf"
                    }
                ]
            },
            {
                "provider": {
                    "name": "TDC",
                    "longName": "TDC",
                    "homePage": "https://tdc.dk",
                    "backgroundColor": "#266baf",
                    "textColor": "white" 
                },
                "frequency": {
                    "downLink": {
                        "start": 773,
                        "end": 788
                    },
                    "upLink": {
                        "start": 718,
                        "end": 733
                    }
                },
                "valid": {
                    "start": "2020-04-04",
                    "end": "2040-04-03"
                },
                "source": [
                    {
                        "name": "Danish Energy Agency",
                        "url": "https://ens.dk/sites/ens.dk/files/Tele/700-900_mhz-tilladelse_-_tdc_net.pdf"
                    }
                ]
            }
        ]
    },
    {
        "band": 20,
        "providers": [
            {
                "provider": {
                    "name": "TT",
                    "longName": "TT-Netværket",
                    "homePage": "https://www.tt-network.dk/",
                    "backgroundColor": "#663989",
                    "textColor": "white" 
                },
                "frequency": {
                    "downLink": {
                        "start": 791,
                        "end": 801
                    },
                    "upLink": {
                        "start": 832,
                        "end": 842
                    }
                },
                "valid": {
                    "start": "2013-01-01",
                    "end": "2034-12-31"
                },
                "source": [
                    {
                        "name": "Danish Energy Agency",
                        "url": "https://ens.dk/sites/ens.dk/files/Tele/tt-netvaerkets_800_mhz_tilladelse_med_bilag.pdf"
                    }
                ]
            },
            {
                "provider": {
                    "name": "TDC",
                    "longName": "TDC",
                    "homePage": "https://tdc.dk",
                    "backgroundColor": "#266baf",
                    "textColor": "white" 
                },
                "frequency": {
                    "downLink": {
                        "start": 801,
                        "end": 821
                    },
                    "upLink": {
                        "start": 842,
                        "end": 862
                    }
                },
                "valid": {
                    "start": "2013-01-01",
                    "end": "2034-12-31"
                },
                "source": [
                    {
                        "name": "Danish Energy Agency",
                        "url": "https://ens.dk/sites/ens.dk/files/Tele/tdc_800_mhz_tilladelse_med_bilag_og_tillaeg.pdf"
                    }
                ]
            }
        ]
    },
    {
        "band": 8,
        "providers": [
            {
                "provider": {
                    "name": "3",
                    "longName": "Hi3G Denmark",
                    "homePage": "https://www.3.dk/",
                    "backgroundColor": "#f37423",
                    "textColor": "white" 
                },
                "frequency": {
                    "downLink": {
                        "start": 945,
                        "end": 955
                    },
                    "upLink": {
                        "start": 900,
                        "end": 910
                    }
                },
                "valid": {
                    "start": "2020-04-01",
                    "end": "2034-12-31"
                },
                "source": [
                    {
                        "name": "Danish Energy Agency",
                        "url": "https://ens.dk/sites/ens.dk/files/Tele/700-900_mhz-tilladelse_-_hi3g.pdf"
                    }
                ]
            },
            {
                "provider": {
                    "name": "TT",
                    "longName": "TT-Netværket",
                    "homePage": "https://www.tt-network.dk/",
                    "backgroundColor": "#663989",
                    "textColor": "white" 
                },
                "frequency": {
                    "downLink": {
                        "start": 925,
                        "end": 935
                    },
                    "upLink": {
                        "start": 880,
                        "end": 890
                    }
                },
                "valid": {
                    "start": "2020-04-01",
                    "end": "2034-12-31"
                },
                "source": [
                    {
                        "name": "Danish Energy Agency",
                        "url": "https://ens.dk/sites/ens.dk/files/Tele/700-900_mhz-tilladelse_-tt-netvaerket.pdf"
                    }
                ]
            },
            {
                "provider": {
                    "name": "TDC",
                    "longName": "TDC",
                    "homePage": "https://tdc.dk",
                    "backgroundColor": "#266baf",
                    "textColor": "white" 
                },
                "frequency": {
                    "downLink": {
                        "start": 935,
                        "end": 945
                    },
                    "upLink": {
                        "start": 890,
                        "end": 900
                    }
                },
                "valid": {
                    "start": "2020-04-01",
                    "end": "2034-12-31"
                },
                "source": [
                    {
                        "name": "Danish Energy Agency",
                        "url": "https://ens.dk/sites/ens.dk/files/Tele/700-900_mhz-tilladelse_-_tdc_net.pdf"
                    }
                ]
            }
        ]
    },
   {
        "band": "76",
        "providers": [
            {
               "provider": {
       "name": "TDC",
                    "longName": "TDC",
                    "homePage": "https://tdc.dk",
                    "backgroundColor": "#266baf",
                    "textColor": "white" 
                },
               "frequency": {
                    "downLink": {
                        "start": 1427,
                        "end": 1452
                    }
                } ,
                "source": [
                    {
                        "name": "Danish Energy Agency",
                        "url": "https://ens.dk/ansvarsomraader/frekvenser/auktioner-og-udbud-frekvenser"
                    }
                ]
            }
        ]
    },
  
    {
        "band": "32",
        "providers": [
            {
               "provider": {
       "name": "TDC",
                    "longName": "TDC",
                    "homePage": "https://tdc.dk",
                    "backgroundColor": "#266baf",
                    "textColor": "white" 
                },
               "frequency": {
                    "downLink": {
                        "start": 1452,
                        "end": 1472
                    }
                } ,
                "source": [
                    {
                        "name": "Danish Energy Agency",
                        "url": "https://ens.dk/ansvarsomraader/frekvenser/auktioner-og-udbud-frekvenser"
                    }
                ]
            },
            {
                "provider": {
                    "name": "TT",
                    "longName": "TT-Netværket",
                    "homePage": "https://www.tt-network.dk/",
                    "backgroundColor": "#663989",
                    "textColor": "white" 
                },
                "frequency": {
                    "downLink": {
                        "start": 1472,
                        "end": 1496
                    }
                } ,
                "technology": [
                    "LTE"
                ],
                "source": [
                    {
                        "name": "Danish Energy Agency",
                        "url": "https://ens.dk/ansvarsomraader/frekvenser/auktioner-og-udbud-frekvenser"
                    }
                ]
            }
        ]
    },
     {
        "band": "75",
        "providers": [
            {
                 "provider": {
                    "name": "TT",
                    "longName": "TT-Netværket",
                    "homePage": "https://www.tt-network.dk/",
                    "backgroundColor": "#663989",
                    "textColor": "white" 
                },
               "frequency": {
                    "downLink": {
                        "start": 1496,
                        "end": 1517
                    }
                } ,
                "source": [
                    {
                        "name": "Danish Energy Agency",
                        "url": "https://ens.dk/ansvarsomraader/frekvenser/auktioner-og-udbud-frekvenser"
                    }
                ]
            }
        ]
    },
    {
        "band": 3,
        "providers": [
            {
                "provider": {
                    "name": "TDC",
                    "longName": "TDC",
                    "homePage": "https://tdc.dk",
                    "backgroundColor": "#266baf",
                    "textColor": "white" 
                },
                "frequency": {
                    "downLink": {
                        "start": 1805,
                        "end": 1825
                    },
                    "upLink": {
                        "start": 1710,
                        "end": 1730
                    }
                },
                "source": [
                    {
                        "name": "Danish Energy Agency",
                        "url": "https://ens.dk/sites/ens.dk/files/Tele/tillaeg_nr_2_til_1800_mhz-tilladelsen.pdf"
                    }
                ]
            },
            {
                "provider": {
                    "name": "3",
                    "longName": "Hi3G Denmark",
                    "homePage": "https://www.3.dk/",
                    "backgroundColor": "#f37423",
                    "textColor": "white" 
                },
                "frequency": {
                    "downLink": {
                        "start": 1825,
                        "end": 1855
                    },
                    "upLink": {
                        "start": 1730,
                        "end": 1760
                    }
                },
                "source": [
                    {
                        "name": "Danish Energy Agency",
                        "url": "https://ens.dk/sites/ens.dk/files/Tele/1800_mhz_tilladelser_samlet.pdf"
                    }
                ]
            },
            {
                "provider": {
                    "name": "TT",
                    "longName": "TT-Netværket",
                    "homePage": "https://www.tt-network.dk/",
                    "backgroundColor": "#663989",
                    "textColor": "white" 
                },
                "frequency": {
                    "downLink": {
                        "start": 1855,
                        "end": 1880
                    },
                    "upLink": {
                        "start": 1760,
                        "end": 1785
                    }
                },
                "source": [
                    {
                        "name": "Danish Energy Agency",
                        "url": "https://ens.dk/sites/ens.dk/files/Tele/1800_mhz_tilladelser_samlet.pdf"
                    }
                ]
            }
        ]
    },
    {
        "band": 1,
        "providers": [
            {
                "provider": {
                    "name": "3",
                    "longName": "Hi3G Denmark",
                    "homePage": "https://www.3.dk/",
                    "backgroundColor": "#f37423",
                    "textColor": "white" 
                },
                "frequency": {
                    "downLink": {
                        "start": 2110,
                        "end": 2130
                    },
                    "upLink": {
                        "start": 1920,
                        "end": 1940
                    }
                },
                "source": [
                    {
                        "name": "Danish Energy Agency",
                        "url": "https://ens.dk/ansvarsomraader/frekvenser/auktioner-og-udbud-frekvenser"
                    }
                ]
            },
            {
                "provider": {
                    "name": "TDC",
                    "longName": "TDC",
                    "homePage": "https://tdc.dk",
                    "backgroundColor": "#266baf",
                    "textColor": "white" 
                },
                "frequency": {
                    "downLink": {
                        "start": 2130,
                        "end": 2150
                    },
                    "upLink": {
                        "start": 1940,
                        "end": 1960
                    }
                },
                "source": [
                    {
                        "name": "Danish Energy Agency",
                        "url": "https://ens.dk/ansvarsomraader/frekvenser/auktioner-og-udbud-frekvenser"
                    }
                ]
            },
            {
                "provider": {
                    "name": "TT",
                    "longName": "TT-Netværket",
                    "homePage": "https://www.tt-network.dk/",
                    "backgroundColor": "#663989",
                    "textColor": "white" 
                },
                "frequency": {
                    "downLink": {
                        "start": 2150,
                        "end": 2170
                    },
                    "upLink": {
                        "start": 1960,
                        "end": 1980
                    }
                },
                "source": [
                    {
                        "name": "Danish Energy Agency",
                        "url": "https://ens.dk/ansvarsomraader/frekvenser/auktioner-og-udbud-frekvenser"
                    }
                ]
            }
        ]
    },
    {
        "band": 40,
        "providers": [
            {
                "provider": {
                    "name": "TDC",
                    "longName": "TDC",
                    "homePage": "https://tdc.dk",
                    "backgroundColor": "#266baf",
                    "textColor": "white" 
                },
                "frequency": {
                    "downLink": {
                        "start": 2300,
                        "end": 2400
                    }
                },
                "source": [
                    {
                        "name": "Danish Energy Agency",
                        "url": "https://ens.dk/ansvarsomraader/frekvenser/auktioner-og-udbud-frekvenser"
                    }
                ]
            }
        ]
    },
    {
        "band": 7,
        "providers": [
            {
                "provider": {
                    "name": "TDC",
                    "longName": "TDC",
                    "homePage": "https://tdc.dk",
                    "backgroundColor": "#266baf",
                    "textColor": "white" 
                },
                "frequency": {
                    "downLink": {
                        "start": 2620,
                        "end": 2640
                    },
                    "upLink": {
                        "start": 2500,
                        "end": 2520
                    }
                },
                "source": [
                    {
                        "name": "Danish Energy Agency",
                        "url": "https://ens.dk/sites/ens.dk/files/Tele/26_ghz_tilladelser_samlet.pdf"
                    }
                ]
            },
            {
                "provider": {
                    "name": "3",
                    "longName": "Hi3G Denmark",
                    "homePage": "https://www.3.dk/",
                    "backgroundColor": "#f37423",
                    "textColor": "white" 
                },
                "frequency": {
                    "downLink": {
                        "start": 2640,
                        "end": 2650
                    },
                    "upLink": {
                        "start": 2520,
                        "end": 2530
                    }
                },
                "source": [
                    {
                        "name": "Danish Energy Agency",
                        "url": "https://ens.dk/sites/ens.dk/files/Tele/26_ghz_tilladelser_samlet.pdf"
                    }
                ]
            },
            {
                "provider": {
                    "name": "TT (Telia)",
                    "longName": "TT-Netværket (Telia)",
                    "homePage": "https://www.tt-network.dk/",
                    "backgroundColor": "#663989",
                    "textColor": "white" 
                },
                "frequency": {
                    "downLink": {
                        "start": 2650,
                        "end": 2670
                    },
                    "upLink": {
                        "start": 2530,
                        "end": 2550
                    }
                },
                "source": [
                    {
                        "name": "Danish Energy Agency",
                        "url": "https://ens.dk/sites/ens.dk/files/Tele/26_ghz_tilladelser_samlet.pdf"
                    }
                ]
            },
            {
                "provider": {
                    "name": "TT (Telenor)",
                    "longName": "TT-Netværket (Telenor)",
                    "homePage": "https://www.tt-network.dk/",
                    "backgroundColor": "#663989",
                    "textColor": "white" 
                },
                "frequency": {
                    "downLink": {
                        "start": 2670,
                        "end": 2690
                    },
                    "upLink": {
                        "start": 2550,
                        "end": 2570
                    }
                },
                "source": [
                    {
                        "name": "Danish Energy Agency",
                        "url": "https://ens.dk/sites/ens.dk/files/Tele/26_ghz_tilladelser_samlet.pdf"
                    }
                ]
            }
        ]
    },
    {
        "band": 38,
        "providers": [
            {
                "provider": {
                    "name": "3",
                    "longName": "Hi3G Denmark",
                    "homePage": "https://www.3.dk/",
                    "backgroundColor": "#f37423",
                    "textColor": "white" 
                },
                "frequency": {
                    "downLink": {
                        "start": 2570,
                        "end": 2595
                    }
                },
                "source": [
                    {
                        "name": "Danish Energy Agency",
                        "url": "https://ens.dk/sites/ens.dk/files/Tele/26_ghz_tilladelser_samlet.pdf"
                    }
                ]
            },
            {
                "provider": {
                    "name": "TT (Telenor)",
                    "longName": "TT-Netværket (Telenor)",
                    "homePage": "https://www.tt-network.dk/",
                    "backgroundColor": "#663989",
                    "textColor": "white" 
                },
                "frequency": {
                    "downLink": {
                        "start": 2595,
                        "end": 2605
                    }
                },
                "source": [
                    {
                        "name": "Danish Energy Agency",
                        "url": "https://ens.dk/sites/ens.dk/files/Tele/26_ghz_tilladelser_samlet.pdf"
                    }
                ]
            },
            {
                "provider": {
                    "name": "TT (Telia)",
                    "longName": "TT-Netværket (Telia)",
                    "homePage": "https://www.tt-network.dk/",
                    "backgroundColor": "#663989",
                    "textColor": "white" 
                },
                "frequency": {
                    "downLink": {
                        "start": 2605,
                        "end": 2620
                    }
                },
                "source": [
                    {
                        "name": "Danish Energy Agency",
                        "url": "https://ens.dk/sites/ens.dk/files/Tele/26_ghz_tilladelser_samlet.pdf"
                    }
                ]
            }
        ]
    },
{
        "band": 78,
        "providers": [
            {
                "provider": {
                    "name": "TDC",
                    "longName": "TDC",
                    "homePage": "https://tdc.dk",
                    "backgroundColor": "#266baf",
                    "textColor": "white" 
                },
                "frequency": {
                    "downLink": {
                        "start": 3410,
                        "end": 3540
                    },
                    "upLink": {
                        "start": 3410,
                        "end": 3540
                    }
                },
                "source": [
                    {
                        "name": "Danish Energy Agency",
                        "url": "https://ens.dk/ansvarsomraader/frekvenser/auktioner-og-udbud-frekvenser"
                    }
                ]
            },
            {
                "provider": {
                    "name": "3",
                    "longName": "Hi3G Denmark",
                    "homePage": "https://www.3.dk/",
                    "backgroundColor": "#f37423",
                    "textColor": "white" 
                },
                "frequency": {
                    "downLink": {
                        "start": 3540,
                        "end": 3660
                    },
                    "upLink": {
                        "start": 3540,
                        "end": 3660
                    }
                },
                "source": [
                    {
                        "name": "Danish Energy Agency",
                        "url": "https://ens.dk/ansvarsomraader/frekvenser/auktioner-og-udbud-frekvenser"
                    }
                ]
            },
            {
                "provider": {
                    "name": "TT",
                    "longName": "TT-Netværket",
                    "homePage": "https://www.tt-network.dk/",
                    "backgroundColor": "#663989",
                    "textColor": "white" 
                },
                "frequency": {
                    "downLink": {
                        "start": 3660,
                        "end": 3800
                    },
                    "upLink": {
                        "start": 3600,
                        "end": 3800
                    }
                },
                "source": [
                    {
                        "name": "Danish Energy Agency",
                        "url": "https://ens.dk/ansvarsomraader/frekvenser/auktioner-og-udbud-frekvenser"
                    }
                ]
            }
        ]
    },
  {
        "band": 258,
        "providers": [
            {
                "provider": {
                    "name": "TDC",
                    "longName": "TDC",
                    "homePage": "https://tdc.dk",
                    "backgroundColor": "#266baf",
                    "textColor": "white" 
                },
                "frequency": {
                    "downLink": {
                        "start": 24650,
                        "end": 25900
                    },
                    "upLink": {
                        "start": 24650,
                        "end": 25900
                    }
                },
                "source": [
                    {
                        "name": "Danish Energy Agency",
                        "url": "https://ens.dk/ansvarsomraader/frekvenser/auktioner-og-udbud-frekvenser"
                    }
                ]
            },
         {
                "provider": {
                    "name": "TT",
                    "longName": "TT-Netværket",
                    "homePage": "https://www.tt-network.dk/",
                    "backgroundColor": "#663989",
                    "textColor": "white" 
                },
                "frequency": {
                    "downLink": {
                        "start": 25900,
                        "end": 26500
                    },
                    "upLink": {
                        "start": 25900,
                        "end": 26500
                    }
                },
                "source": [
                    {
                        "name": "Danish Energy Agency",
                        "url": "https://ens.dk/ansvarsomraader/frekvenser/auktioner-og-udbud-frekvenser"
                    }
                ]
            },
            {
                "provider": {
                    "name": "3",
                    "longName": "Hi3G Denmark",
                    "homePage": "https://www.3.dk/",
                    "backgroundColor": "#f37423",
                    "textColor": "white" 
                },
                "frequency": {
                    "downLink": {
                        "start": 26500,
                        "end": 27500
                    },
                    "upLink": {
                        "start": 26500,
                        "end": 27500
                    }
                },
                "source": [
                    {
                        "name": "Danish Energy Agency",
                        "url": "https://ens.dk/ansvarsomraader/frekvenser/auktioner-og-udbud-frekvenser"
                    }
                ]
            }
        ]
    },

]
